migadu_mcp/__init__.py
migadu_mcp/config.py
migadu_mcp/main.py
migadu_mcp/client/__init__.py
migadu_mcp/client/migadu_client.py
migadu_mcp/services/__init__.py
migadu_mcp/services/alias_service.py
migadu_mcp/services/identity_service.py
migadu_mcp/services/mailbox_service.py
migadu_mcp/services/rewrite_service.py
migadu_mcp/services/service_factory.py
migadu_mcp/tools/__init__.py
migadu_mcp/tools/alias_tools.py
migadu_mcp/tools/identity_tools.py
migadu_mcp/tools/mailbox_tools.py
migadu_mcp/tools/resource_tools.py
migadu_mcp/tools/rewrite_tools.py
migadu_mcp/utils/bulk_processing.py
migadu_mcp/utils/context_protection.py
migadu_mcp/utils/email_parsing.py
migadu_mcp/utils/schemas.py
migadu_mcp/utils/tool_helpers.py
migadu_mcp-3.5.1.dist-info/licenses/LICENSE
migadu_mcp-3.5.1.dist-info/METADATA
migadu_mcp-3.5.1.dist-info/WHEEL
migadu_mcp-3.5.1.dist-info/entry_points.txt
migadu_mcp-3.5.1.dist-info/top_level.txt
migadu_mcp-3.5.1.dist-info/RECORD
