Metadata-Version: 2.4
Name: migadu-mcp
Version: 3.5.1
Summary: Professional FastMCP server for comprehensive Migadu email management with Context logging, tool annotations, and testing infrastructure
Author-email: Michael Broel <Michael@Michaelzag.com>
License: MIT
Project-URL: Homepage, https://github.com/Michaelzag/migadu-mcp
Project-URL: Repository, https://github.com/Michaelzag/migadu-mcp
Project-URL: Issues, https://github.com/Michaelzag/migadu-mcp/issues
Keywords: migadu,email,mcp,server,mailbox,alias,identity
Classifier: Development Status :: 5 - Production/Stable
Classifier: Intended Audience :: Developers
Classifier: Intended Audience :: System Administrators
Classifier: License :: OSI Approved :: MIT License
Classifier: Programming Language :: Python :: 3
Classifier: Programming Language :: Python :: 3.13
Classifier: Topic :: Communications :: Email
Classifier: Topic :: Software Development :: Libraries :: Python Modules
Classifier: Topic :: System :: Systems Administration
Requires-Python: >=3.13
License-File: LICENSE
Requires-Dist: fastmcp>=2.8.1
Requires-Dist: httpx>=0.28.1
Requires-Dist: pydantic>=2.0.0
Requires-Dist: email-validator>=2.0.0
Dynamic: license-file
